setup.py
hexagons/__init__.py
hexagons/ascii.py
hexagons/coordinate.py
hexagons/grid.py
hexagons/sample.py
hexagons.egg-info/PKG-INFO
hexagons.egg-info/SOURCES.txt
hexagons.egg-info/dependency_links.txt
hexagons.egg-info/requires.txt
hexagons.egg-info/top_level.txt