Metadata-Version: 1.0
Name: hexagons
Version: 0.1.0.0
Summary: Hexagon grids for games
Home-page: https://github.com/diorge/hexagons
Author: Diorge Brognara
Author-email: diorge.bs@gmail.com
License: MIT License
Platform: UNKNOWN
